<?xml version="1.0" encoding="UTF-8"?>
<yearIR year="1981" xmlns:xsi="http://www.w3.org/2001/XMLSchema-instance" xsi:noNamespaceSchemaLocation="http://imo.dmfa.si/schemas/YearIndividualResults.xsd">
<contestant id="16615">
<code>AUT</code><name>Andreas</name><surname>Binder</surname><problem1>7</problem1><problem2>7</problem2><problem3>7</problem3><problem4>7</problem4><problem5>7</problem5><problem6>7</problem6><total>42</total><rank>1</rank><award>Gold medal</award></contestant><contestant id="16620">
<code>AUT</code><name>Harald</name><surname>Skarke</surname><problem1>7</problem1><problem2>7</problem2><problem3>7</problem3><problem4>7</problem4><problem5>7</problem5><problem6>7</problem6><total>42</total><rank>1</rank><award>Gold medal</award></contestant><contestant id="10437">
<code>BRA</code><name>Nicolau Corçao</name><surname>Saldanha</surname><problem1>7</problem1><problem2>7</problem2><problem3>7</problem3><problem4>7</problem4><problem5>7</problem5><problem6>7</problem6><total>42</total><rank>1</rank><award>Gold medal</award></contestant><contestant id="16632">
<code>BGR</code><name>Georgi</name><surname>Iordanov Vodev</surname><problem1>7</problem1><problem2>7</problem2><problem3>7</problem3><problem4>7</problem4><problem5>7</problem5><problem6>7</problem6><total>42</total><rank>1</rank><award>Gold medal</award></contestant><contestant id="10444">
<code>CAN</code><name>David</name><surname>Ash</surname><problem1>7</problem1><problem2>7</problem2><problem3>7</problem3><problem4>7</problem4><problem5>7</problem5><problem6>7</problem6><total>42</total><rank>1</rank><award>Gold medal</award></contestant><contestant id="10449">
<code>CAN</code><name>Georges</name><surname>Gonthier</surname><problem1>7</problem1><problem2>7</problem2><problem3>7</problem3><problem4>7</problem4><problem5>7</problem5><problem6>7</problem6><total>42</total><rank>1</rank><award>Gold medal</award></contestant><contestant id="16658">
<code>CZS</code><name>Jan</name><surname>Nekovář</surname><problem1>7</problem1><problem2>7</problem2><problem3>7</problem3><problem4>7</problem4><problem5>7</problem5><problem6>7</problem6><total>42</total><rank>1</rank><award>Gold medal</award></contestant><contestant id="16670">
<code>FRA</code><name>Jean-François</name><surname>Bertin</surname><problem1>7</problem1><problem2>7</problem2><problem3>7</problem3><problem4>7</problem4><problem5>7</problem5><problem6>7</problem6><total>42</total><rank>1</rank><award>Gold medal</award></contestant><contestant id="16674">
<code>FRA</code><name>Pierre</name><surname>Lavaurs</surname><problem1>7</problem1><problem2>7</problem2><problem3>7</problem3><problem4>7</problem4><problem5>7</problem5><problem6>7</problem6><total>42</total><rank>1</rank><award>Gold medal</award></contestant><contestant id="12870">
<code>GER</code><name>Hartmut</name><surname>Maennel</surname><problem1>7</problem1><problem2>7</problem2><problem3>7</problem3><problem4>7</problem4><problem5>7</problem5><problem6>7</problem6><total>42</total><rank>1</rank><award>Gold medal</award></contestant><contestant id="12871">
<code>GER</code><name>Martin</name><surname>Neschen</surname><problem1>7</problem1><problem2>7</problem2><problem3>7</problem3><problem4>7</problem4><problem5>7</problem5><problem6>7</problem6><total>42</total><rank>1</rank><award>Gold medal</award></contestant><contestant id="12874">
<code>GER</code><name>Günter M.</name><surname>Ziegler</surname><problem1>7</problem1><problem2>7</problem2><problem3>7</problem3><problem4>7</problem4><problem5>7</problem5><problem6>7</problem6><total>42</total><rank>1</rank><award>Gold medal</award></contestant><contestant id="10452">
<code>HUN</code><name>Gábor</name><surname>Simonyi</surname><problem1>7</problem1><problem2>7</problem2><problem3>7</problem3><problem4>7</problem4><problem5>7</problem5><problem6>7</problem6><total>42</total><rank>1</rank><award>Gold medal</award></contestant><contestant id="16684">
<code>ISR</code><name>Yossi</name><surname>Azar</surname><problem1>7</problem1><problem2>7</problem2><problem3>7</problem3><problem4>7</problem4><problem5>7</problem5><problem6>7</problem6><total>42</total><rank>1</rank><award>Gold medal</award></contestant><contestant id="16690">
<code>LUX</code><name>Michel</name><surname>Dauphin</surname><problem1>7</problem1><problem2>7</problem2><problem3>7</problem3><problem4>7</problem4><problem5>7</problem5><problem6>7</problem6><total>42</total><rank>1</rank><award>Gold medal</award></contestant><contestant id="15996">
<code>POL</code><name>Jarosław</name><surname>Wróblewski</surname><problem1>7</problem1><problem2>7</problem2><problem3>7</problem3><problem4>7</problem4><problem5>7</problem5><problem6>7</problem6><total>42</total><rank>1</rank><award>Gold medal</award></contestant><contestant id="16710">
<code>USS</code><name>Valery</name><surname>Alexeev</surname><problem1>7</problem1><problem2>7</problem2><problem3>7</problem3><problem4>7</problem4><problem5>7</problem5><problem6>7</problem6><total>42</total><rank>1</rank><award>Gold medal</award></contestant><contestant id="16715">
<code>USS</code><name>Yuri</name><surname>Chekanov</surname><problem1>7</problem1><problem2>7</problem2><problem3>7</problem3><problem4>7</problem4><problem5>7</problem5><problem6>7</problem6><total>42</total><rank>1</rank><award>Gold medal</award></contestant><contestant id="16714">
<code>USS</code><name>Mikhail</name><surname>Grinchuk</surname><problem1>7</problem1><problem2>7</problem2><problem3>7</problem3><problem4>7</problem4><problem5>7</problem5><problem6>7</problem6><total>42</total><rank>1</rank><award>Gold medal</award></contestant><contestant id="11100">
<code>UNK</code><name>Mark David</name><surname>Bennet</surname><problem1>7</problem1><problem2>7</problem2><problem3>7</problem3><problem4>7</problem4><problem5>7</problem5><problem6>7</problem6><total>42</total><rank>1</rank><award>Gold medal</award></contestant><contestant id="11101">
<code>UNK</code><name>William Timothy (Tim)</name><surname>Gowers</surname><problem1>7</problem1><problem2>7</problem2><problem3>7</problem3><problem4>7</problem4><problem5>7</problem5><problem6>7</problem6><total>42</total><rank>1</rank><award>Gold medal</award></contestant><contestant id="10464">
<code>USA</code><name>Noam</name><surname>Elkies</surname><problem1>7</problem1><problem2>7</problem2><problem3>7</problem3><problem4>7</problem4><problem5>7</problem5><problem6>7</problem6><total>42</total><rank>1</rank><award>Gold medal</award></contestant><contestant id="10465">
<code>USA</code><name>Benji</name><surname>Fisher</surname><problem1>7</problem1><problem2>7</problem2><problem3>7</problem3><problem4>7</problem4><problem5>7</problem5><problem6>7</problem6><total>42</total><rank>1</rank><award>Gold medal</award></contestant><contestant id="10466">
<code>USA</code><name>Brian</name><surname>Hunt</surname><problem1>7</problem1><problem2>7</problem2><problem3>7</problem3><problem4>7</problem4><problem5>7</problem5><problem6>7</problem6><total>42</total><rank>1</rank><award>Gold medal</award></contestant><contestant id="10467">
<code>USA</code><name>Jeremy</name><surname>Primer</surname><problem1>7</problem1><problem2>7</problem2><problem3>7</problem3><problem4>7</problem4><problem5>7</problem5><problem6>7</problem6><total>42</total><rank>1</rank><award>Gold medal</award></contestant><contestant id="10474">
<code>YUG</code><name>Mladen</name><surname>Despić</surname><problem1>7</problem1><problem2>7</problem2><problem3>7</problem3><problem4>7</problem4><problem5>7</problem5><problem6>7</problem6><total>42</total><rank>1</rank><award>Gold medal</award></contestant><contestant id="16616">
<code>AUT</code><name>Martin</name><surname>Goldstern</surname><problem1>7</problem1><problem2>7</problem2><problem3>6</problem3><problem4>7</problem4><problem5>7</problem5><problem6>7</problem6><total>41</total><rank>27</rank><award>Gold medal</award></contestant><contestant id="16617">
<code>AUT</code><name>Günter</name><surname>Pollak</surname><problem1>7</problem1><problem2>7</problem2><problem3>6</problem3><problem4>7</problem4><problem5>7</problem5><problem6>7</problem6><total>41</total><rank>27</rank><award>Gold medal</award></contestant><contestant id="16638">
<code>BGR</code><name>Todor</name><surname>Petkov Mitev</surname><problem1></problem1><problem2></problem2><problem3></problem3><problem4></problem4><problem5></problem5><problem6></problem6><total>41</total><rank>27</rank><award>Gold medal</award></contestant><contestant id="16661">
<code>FIN</code><name>Taneli</name><surname>Huuskonen</surname><problem1></problem1><problem2></problem2><problem3></problem3><problem4></problem4><problem5></problem5><problem6></problem6><total>41</total><rank>27</rank><award>Gold medal</award></contestant><contestant id="12867">
<code>GER</code><name>Ortwin</name><surname>Gasper</surname><problem1></problem1><problem2></problem2><problem3></problem3><problem4></problem4><problem5></problem5><problem6></problem6><total>41</total><rank>27</rank><award>Gold medal</award></contestant><contestant id="12872">
<code>GER</code><name>Bernhard</name><surname>Raaf</surname><problem1></problem1><problem2></problem2><problem3></problem3><problem4></problem4><problem5></problem5><problem6></problem6><total>41</total><rank>27</rank><award>Gold medal</award></contestant><contestant id="10453">
<code>HUN</code><name>Gyula</name><surname>Károlyi</surname><problem1></problem1><problem2></problem2><problem3></problem3><problem4></problem4><problem5></problem5><problem6></problem6><total>41</total><rank>27</rank><award>Gold medal</award></contestant><contestant id="10454">
<code>HUN</code><name>Endre</name><surname>Szabó</surname><problem1></problem1><problem2></problem2><problem3></problem3><problem4></problem4><problem5></problem5><problem6></problem6><total>41</total><rank>27</rank><award>Gold medal</award></contestant><contestant id="15991">
<code>POL</code><name>Tomasz</name><surname>Hrycak</surname><problem1></problem1><problem2></problem2><problem3></problem3><problem4></problem4><problem5></problem5><problem6></problem6><total>41</total><rank>27</rank><award>Gold medal</award></contestant><contestant id="11106">
<code>UNK</code><name>Jeremy Charles</name><surname>Rickard</surname><problem1></problem1><problem2></problem2><problem3></problem3><problem4></problem4><problem5></problem5><problem6></problem6><total>41</total><rank>27</rank><award>Gold medal</award></contestant><contestant id="16633">
<code>BGR</code><name>Krasimir</name><surname>Georgiev Ianakiev</surname><problem1></problem1><problem2></problem2><problem3></problem3><problem4></problem4><problem5></problem5><problem6></problem6><total>40</total><rank>37</rank><award>Silver medal</award></contestant><contestant id="16655">
<code>CZS</code><name>Igor</name><surname>Kříž</surname><problem1>7</problem1><problem2>7</problem2><problem3>7</problem3><problem4>6</problem4><problem5>6</problem5><problem6>7</problem6><total>40</total><rank>37</rank><award>Silver medal</award></contestant><contestant id="10455">
<code>HUN</code><name>Gábor</name><surname>Tardos</surname><problem1></problem1><problem2></problem2><problem3></problem3><problem4></problem4><problem5></problem5><problem6></problem6><total>40</total><rank>37</rank><award>Silver medal</award></contestant><contestant id="12868">
<code>GER</code><name>Martin</name><surname>Kreuzer</surname><problem1></problem1><problem2></problem2><problem3></problem3><problem4></problem4><problem5></problem5><problem6></problem6><total>39</total><rank>40</rank><award>Silver medal</award></contestant><contestant id="10468">
<code>USA</code><name>Gregg</name><surname>Patruno</surname><problem1></problem1><problem2></problem2><problem3></problem3><problem4></problem4><problem5></problem5><problem6></problem6><total>39</total><rank>40</rank><award>Silver medal</award></contestant><contestant id="10470">
<code>USA</code><name>Richard</name><surname>Stong</surname><problem1></problem1><problem2></problem2><problem3></problem3><problem4></problem4><problem5></problem5><problem6></problem6><total>39</total><rank>40</rank><award>Silver medal</award></contestant><contestant id="10436">
<code>BEL</code><name>Bernard</name><surname>Steenis</surname><problem1></problem1><problem2></problem2><problem3></problem3><problem4></problem4><problem5></problem5><problem6></problem6><total>38</total><rank>43</rank><award>Silver medal</award></contestant><contestant id="16657">
<code>CZS</code><name>Jozef</name><surname>Bednárik</surname><problem1>7</problem1><problem2>7</problem2><problem3>7</problem3><problem4>7</problem4><problem5>3</problem5><problem6>7</problem6><total>38</total><rank>43</rank><award>Silver medal</award></contestant><contestant id="16656">
<code>CZS</code><name>Petr</name><surname>Couf</surname><problem1>7</problem1><problem2>7</problem2><problem3>3</problem3><problem4>7</problem4><problem5>7</problem5><problem6>7</problem6><total>38</total><rank>43</rank><award>Silver medal</award></contestant><contestant id="16666">
<code>FIN</code><name>Eero</name><surname>Saksman</surname><problem1></problem1><problem2></problem2><problem3></problem3><problem4></problem4><problem5></problem5><problem6></problem6><total>38</total><rank>43</rank><award>Silver medal</award></contestant><contestant id="16706">
<code>SWE</code><name>Johan</name><surname>Råde</surname><problem1></problem1><problem2></problem2><problem3></problem3><problem4></problem4><problem5></problem5><problem6></problem6><total>38</total><rank>43</rank><award>Silver medal</award></contestant><contestant id="11103">
<code>UNK</code><name>Peter Benedict</name><surname>Kronheimer</surname><problem1></problem1><problem2></problem2><problem3></problem3><problem4></problem4><problem5></problem5><problem6></problem6><total>38</total><rank>43</rank><award>Silver medal</award></contestant><contestant id="11105">
<code>UNK</code><name>Stephen John</name><surname>Montgomery-Smith</surname><problem1></problem1><problem2></problem2><problem3></problem3><problem4></problem4><problem5></problem5><problem6></problem6><total>38</total><rank>43</rank><award>Silver medal</award></contestant><contestant id="16619">
<code>AUT</code><name>Josef</name><surname>Schicho</surname><problem1>7</problem1><problem2>7</problem2><problem3>2</problem3><problem4>7</problem4><problem5>7</problem5><problem6>7</problem6><total>37</total><rank>50</rank><award>Silver medal</award></contestant><contestant id="16623">
<code>BEL</code><name>Ivan</name><surname>Deman</surname><problem1></problem1><problem2></problem2><problem3></problem3><problem4></problem4><problem5></problem5><problem6></problem6><total>37</total><rank>50</rank><award>Silver medal</award></contestant><contestant id="16636">
<code>BGR</code><name>Emil</name><surname>Milanov Kolev</surname><problem1></problem1><problem2></problem2><problem3></problem3><problem4></problem4><problem5></problem5><problem6></problem6><total>37</total><rank>50</rank><award>Silver medal</award></contestant><contestant id="10450">
<code>CAN</code><name>Charles S.</name><surname>Timar</surname><problem1>7</problem1><problem2>6</problem2><problem3>5</problem3><problem4>6</problem4><problem5>6</problem5><problem6>7</problem6><total>37</total><rank>50</rank><award>Silver medal</award></contestant><contestant id="12869">
<code>GER</code><name>Bernhard</name><surname>Leeb</surname><problem1></problem1><problem2></problem2><problem3></problem3><problem4></problem4><problem5></problem5><problem6></problem6><total>37</total><rank>50</rank><award>Silver medal</award></contestant><contestant id="10458">
<code>NLD</code><name>Tonny</name><surname>Hurkens</surname><problem1>7</problem1><problem2>7</problem2><problem3>2</problem3><problem4>7</problem4><problem5>7</problem5><problem6>7</problem6><total>37</total><rank>50</rank><award>Silver medal</award></contestant><contestant id="11104">
<code>UNK</code><name>Imre Bennett</name><surname>Leader</surname><problem1></problem1><problem2></problem2><problem3></problem3><problem4></problem4><problem5></problem5><problem6></problem6><total>37</total><rank>50</rank><award>Silver medal</award></contestant><contestant id="10477">
<code>YUG</code><name>Nina</name><surname>Ležaić</surname><problem1></problem1><problem2></problem2><problem3></problem3><problem4></problem4><problem5></problem5><problem6></problem6><total>37</total><rank>50</rank><award>Silver medal</award></contestant><contestant id="16618">
<code>AUT</code><name>Heinz</name><surname>Roitner</surname><problem1>7</problem1><problem2>7</problem2><problem3>1</problem3><problem4>7</problem4><problem5>7</problem5><problem6>7</problem6><total>36</total><rank>58</rank><award>Silver medal</award></contestant><contestant id="10459">
<code>NLD</code><name>Daan</name><surname>Krammer</surname><problem1>1</problem1><problem2>7</problem2><problem3>7</problem3><problem4>7</problem4><problem5>7</problem5><problem6>7</problem6><total>36</total><rank>58</rank><award>Silver medal</award></contestant><contestant id="10463">
<code>NLD</code><name>Paul</name><surname>van der Wagt</surname><problem1>6</problem1><problem2>7</problem2><problem3>5</problem3><problem4>4</problem4><problem5>7</problem5><problem6>7</problem6><total>36</total><rank>58</rank><award>Silver medal</award></contestant><contestant id="15992">
<code>POL</code><name>Roman</name><surname>Kapuściński</surname><problem1></problem1><problem2></problem2><problem3></problem3><problem4></problem4><problem5></problem5><problem6></problem6><total>36</total><rank>58</rank><award>Silver medal</award></contestant><contestant id="0">
<code>ROU</code><name></name><surname></surname><problem1></problem1><problem2></problem2><problem3></problem3><problem4></problem4><problem5></problem5><problem6></problem6><total>36</total><rank>58</rank><award></award>
</contestant><contestant id="16712">
<code>USS</code><name>Yuri</name><surname>Ekishev</surname><problem1></problem1><problem2></problem2><problem3></problem3><problem4></problem4><problem5></problem5><problem6></problem6><total>36</total><rank>58</rank><award>Silver medal</award></contestant><contestant id="11102">
<code>UNK</code><name>Ian Robert Hart</name><surname>Jackson</surname><problem1></problem1><problem2></problem2><problem3></problem3><problem4></problem4><problem5></problem5><problem6></problem6><total>36</total><rank>58</rank><award>Silver medal</award></contestant><contestant id="10448">
<code>CAN</code><name>John</name><surname>Chew</surname><problem1>7</problem1><problem2>7</problem2><problem3>2</problem3><problem4>6</problem4><problem5>6</problem5><problem6>7</problem6><total>35</total><rank>65</rank><award>Silver medal</award></contestant><contestant id="15989">
<code>POL</code><name>Witold</name><surname>Biedrzycki</surname><problem1></problem1><problem2></problem2><problem3></problem3><problem4></problem4><problem5></problem5><problem6></problem6><total>35</total><rank>65</rank><award>Silver medal</award></contestant><contestant id="15995">
<code>POL</code><name>Jarosław</name><surname>Świątek</surname><problem1></problem1><problem2></problem2><problem3></problem3><problem4></problem4><problem5></problem5><problem6></problem6><total>35</total><rank>65</rank><award>Silver medal</award></contestant><contestant id="0">
<code>ROU</code><name></name><surname></surname><problem1></problem1><problem2></problem2><problem3></problem3><problem4></problem4><problem5></problem5><problem6></problem6><total>35</total><rank>65</rank><award></award>
</contestant><contestant id="16713">
<code>USS</code><name>Airat</name><surname>Chanyshev</surname><problem1></problem1><problem2></problem2><problem3></problem3><problem4></problem4><problem5></problem5><problem6></problem6><total>35</total><rank>65</rank><award>Silver medal</award></contestant><contestant id="10469">
<code>USA</code><name>James</name><surname>Roche</surname><problem1></problem1><problem2></problem2><problem3></problem3><problem4></problem4><problem5></problem5><problem6></problem6><total>35</total><rank>65</rank><award>Silver medal</award></contestant><contestant id="10478">
<code>YUG</code><name>Nikola</name><surname>Miljković</surname><problem1></problem1><problem2></problem2><problem3></problem3><problem4></problem4><problem5></problem5><problem6></problem6><total>35</total><rank>65</rank><award>Silver medal</award></contestant><contestant id="16634">
<code>BGR</code><name>Alexander</name><surname>Nenov Ivanov</surname><problem1></problem1><problem2></problem2><problem3></problem3><problem4></problem4><problem5></problem5><problem6></problem6><total>34</total><rank>72</rank><award>Silver medal</award></contestant><contestant id="16648">
<code>CUB</code><name>Jose I.</name><surname>Ariza</surname><problem1></problem1><problem2></problem2><problem3></problem3><problem4></problem4><problem5></problem5><problem6></problem6><total>34</total><rank>72</rank><award>Silver medal</award></contestant><contestant id="16637">
<code>BGR</code><name>Emilia</name><surname>Grigorova Ivanova</surname><problem1></problem1><problem2></problem2><problem3></problem3><problem4></problem4><problem5></problem5><problem6></problem6><total>33</total><rank>74</rank><award>Bronze medal</award></contestant><contestant id="16667">
<code>FIN</code><name>Heikki</name><surname>Tuuri</surname><problem1></problem1><problem2></problem2><problem3></problem3><problem4></problem4><problem5></problem5><problem6></problem6><total>33</total><rank>74</rank><award>Bronze medal</award></contestant><contestant id="0">
<code>ROU</code><name></name><surname></surname><problem1></problem1><problem2></problem2><problem3></problem3><problem4></problem4><problem5></problem5><problem6></problem6><total>33</total><rank>74</rank><award></award>
</contestant><contestant id="16711">
<code>USS</code><name>Andrei</name><surname>Aralkin</surname><problem1></problem1><problem2></problem2><problem3></problem3><problem4></problem4><problem5></problem5><problem6></problem6><total>33</total><rank>74</rank><award>Bronze medal</award></contestant><contestant id="10471">
<code>USA</code><name>David</name><surname>Yuen</surname><problem1></problem1><problem2></problem2><problem3></problem3><problem4></problem4><problem5></problem5><problem6></problem6><total>33</total><rank>74</rank><award>Bronze medal</award></contestant><contestant id="16631">
<code>BGR</code><name>Miroslav</name><surname>Tsanov Iotov</surname><problem1></problem1><problem2></problem2><problem3></problem3><problem4></problem4><problem5></problem5><problem6></problem6><total>32</total><rank>79</rank><award>Bronze medal</award></contestant><contestant id="16659">
<code>CZS</code><name>Jiří</name><surname>Sgall</surname><problem1>0</problem1><problem2>7</problem2><problem3>7</problem3><problem4>7</problem4><problem5>5</problem5><problem6>6</problem6><total>32</total><rank>79</rank><award>Bronze medal</award></contestant><contestant id="16685">
<code>ISR</code><name>Dan</name><surname>Abramovich</surname><problem1></problem1><problem2></problem2><problem3></problem3><problem4></problem4><problem5></problem5><problem6></problem6><total>32</total><rank>79</rank><award>Bronze medal</award></contestant><contestant id="0">
<code>ROU</code><name></name><surname></surname><problem1></problem1><problem2></problem2><problem3></problem3><problem4></problem4><problem5></problem5><problem6></problem6><total>32</total><rank>79</rank><award></award>
</contestant><contestant id="16703">
<code>SWE</code><name>Hans-Olof</name><surname>Kuylenstierna</surname><problem1></problem1><problem2></problem2><problem3></problem3><problem4></problem4><problem5></problem5><problem6></problem6><total>32</total><rank>79</rank><award>Bronze medal</award></contestant><contestant id="16704">
<code>SWE</code><name>Anders</name><surname>Rantzer</surname><problem1></problem1><problem2></problem2><problem3></problem3><problem4></problem4><problem5></problem5><problem6></problem6><total>32</total><rank>79</rank><award>Bronze medal</award></contestant><contestant id="10475">
<code>YUG</code><name>Nebojša</name><surname>Elez</surname><problem1></problem1><problem2></problem2><problem3></problem3><problem4></problem4><problem5></problem5><problem6></problem6><total>32</total><rank>79</rank><award>Bronze medal</award></contestant><contestant id="16664">
<code>FIN</code><name>Jyrki</name><surname>Lahtonen</surname><problem1></problem1><problem2></problem2><problem3></problem3><problem4></problem4><problem5></problem5><problem6></problem6><total>31</total><rank>86</rank><award>Bronze medal</award></contestant><contestant id="16687">
<code>ISR</code><name>Noam</name><surname>Kalmanson</surname><problem1></problem1><problem2></problem2><problem3></problem3><problem4></problem4><problem5></problem5><problem6></problem6><total>31</total><rank>86</rank><award>Bronze medal</award></contestant><contestant id="10473">
<code>YUG</code><name>Ivica</name><surname>Bošnjak</surname><problem1></problem1><problem2></problem2><problem3></problem3><problem4></problem4><problem5></problem5><problem6></problem6><total>31</total><rank>86</rank><award>Bronze medal</award></contestant><contestant id="16622">
<code>AUT</code><name>Kuno</name><surname>Zhuber - Okrog</surname><problem1>6</problem1><problem2>7</problem2><problem3>0</problem3><problem4>5</problem4><problem5>5</problem5><problem6>7</problem6><total>30</total><rank>89</rank><award>Bronze medal</award></contestant><contestant id="10451">
<code>CAN</code><name>Julian</name><surname>West</surname><problem1>1</problem1><problem2>2</problem2><problem3>5</problem3><problem4>7</problem4><problem5>7</problem5><problem6>7</problem6><total>29</total><rank>90</rank><award>Bronze medal</award></contestant><contestant id="16668">
<code>FRA</code><name>Anne-Marie</name><surname>Aubert</surname><problem1></problem1><problem2></problem2><problem3></problem3><problem4></problem4><problem5></problem5><problem6></problem6><total>29</total><rank>90</rank><award>Bronze medal</award></contestant><contestant id="16673">
<code>FRA</code><name>Sinnou</name><surname>David</surname><problem1></problem1><problem2></problem2><problem3></problem3><problem4></problem4><problem5></problem5><problem6></problem6><total>29</total><rank>90</rank><award>Bronze medal</award></contestant><contestant id="16689">
<code>ISR</code><name>Yuri</name><surname>Lev</surname><problem1></problem1><problem2></problem2><problem3></problem3><problem4></problem4><problem5></problem5><problem6></problem6><total>29</total><rank>90</rank><award>Bronze medal</award></contestant><contestant id="10435">
<code>AUS</code><name>Richard</name><surname>Wilson</surname><problem1></problem1><problem2></problem2><problem3></problem3><problem4></problem4><problem5></problem5><problem6></problem6><total>28</total><rank>94</rank><award>Bronze medal</award></contestant><contestant id="16635">
<code>BGR</code><name>Dimiter</name><surname>Kostadinov Statelov</surname><problem1></problem1><problem2></problem2><problem3></problem3><problem4></problem4><problem5></problem5><problem6></problem6><total>28</total><rank>94</rank><award>Bronze medal</award></contestant><contestant id="12873">
<code>GER</code><name>Michael</name><surname>Roth</surname><problem1></problem1><problem2></problem2><problem3></problem3><problem4></problem4><problem5></problem5><problem6></problem6><total>28</total><rank>94</rank><award>Bronze medal</award></contestant><contestant id="15994">
<code>POL</code><name>Aleksander</name><surname>Maliszewski</surname><problem1></problem1><problem2></problem2><problem3></problem3><problem4></problem4><problem5></problem5><problem6></problem6><total>28</total><rank>94</rank><award>Bronze medal</award></contestant><contestant id="16705">
<code>SWE</code><name>Mikael</name><surname>Rittri</surname><problem1></problem1><problem2></problem2><problem3></problem3><problem4></problem4><problem5></problem5><problem6></problem6><total>28</total><rank>94</rank><award>Bronze medal</award></contestant><contestant id="16660">
<code>FIN</code><name>Iiro</name><surname>Honkala</surname><problem1></problem1><problem2></problem2><problem3></problem3><problem4></problem4><problem5></problem5><problem6></problem6><total>27</total><rank>99</rank><award>Bronze medal</award></contestant><contestant id="10460">
<code>NLD</code><name>Bart</name><surname>van de Leemput</surname><problem1>1</problem1><problem2>7</problem2><problem3>0</problem3><problem4>6</problem4><problem5>7</problem5><problem6>6</problem6><total>27</total><rank>99</rank><award>Bronze medal</award></contestant><contestant id="11107">
<code>UNK</code><name>Stephen Paul (Paul)</name><surname>Smith</surname><problem1></problem1><problem2></problem2><problem3></problem3><problem4></problem4><problem5></problem5><problem6></problem6><total>27</total><rank>99</rank><award>Bronze medal</award></contestant><contestant id="16671">
<code>FRA</code><name>Hervé</name><surname>Bonnaud</surname><problem1></problem1><problem2></problem2><problem3></problem3><problem4></problem4><problem5></problem5><problem6></problem6><total>26</total><rank>102</rank><award>Bronze medal</award></contestant><contestant id="10472">
<code>YUG</code><name>Igor</name><surname>Aurer</surname><problem1></problem1><problem2></problem2><problem3></problem3><problem4></problem4><problem5></problem5><problem6></problem6><total>26</total><rank>102</rank><award>Bronze medal</award></contestant><contestant id="16625">
<code>BEL</code><name>Michel</name><surname>Jacquemin</surname><problem1></problem1><problem2></problem2><problem3></problem3><problem4></problem4><problem5></problem5><problem6></problem6><total>25</total><rank>104</rank><award></award></contestant><contestant id="10445">
<code>CAN</code><name>Arthur</name><surname>Baragar</surname><problem1>0</problem1><problem2>7</problem2><problem3>0</problem3><problem4>5</problem4><problem5>6</problem5><problem6>7</problem6><total>25</total><rank>104</rank><award></award></contestant><contestant id="16647">
<code>CUB</code><name>Andrei</name><surname>Martinez</surname><problem1></problem1><problem2></problem2><problem3></problem3><problem4></problem4><problem5></problem5><problem6></problem6><total>25</total><rank>104</rank><award></award></contestant><contestant id="16686">
<code>ISR</code><name>Yuri</name><surname>Rabinovitch</surname><problem1></problem1><problem2></problem2><problem3></problem3><problem4></problem4><problem5></problem5><problem6></problem6><total>25</total><rank>104</rank><award></award></contestant><contestant id="10456">
<code>NLD</code><name>Erik</name><surname>Admiraal</surname><problem1>0</problem1><problem2>7</problem2><problem3>0</problem3><problem4>5</problem4><problem5>7</problem5><problem6>6</problem6><total>25</total><rank>105</rank><award></award></contestant><contestant id="10457">
<code>NLD</code><name>Bram</name><surname>Bouwens</surname><problem1>6</problem1><problem2>6</problem2><problem3>1</problem3><problem4>5</problem4><problem5>7</problem5><problem6>0</problem6><total>25</total><rank>104</rank><award></award></contestant><contestant id="16624">
<code>BEL</code><name>Michel</name><surname>Goemans</surname><problem1></problem1><problem2></problem2><problem3></problem3><problem4></problem4><problem5></problem5><problem6></problem6><total>24</total><rank>110</rank><award></award></contestant><contestant id="16676">
<code>HEL</code><name>Sarantos</name><surname>Kapidakis</surname><problem1></problem1><problem2></problem2><problem3></problem3><problem4></problem4><problem5></problem5><problem6></problem6><total>24</total><rank>110</rank><award></award></contestant><contestant id="15993">
<code>POL</code><name>Izabella</name><surname>Łaba</surname><problem1></problem1><problem2></problem2><problem3></problem3><problem4></problem4><problem5></problem5><problem6></problem6><total>24</total><rank>110</rank><award></award></contestant><contestant id="10438">
<code>BRA</code><name>Helder</name><surname>Wenceslau</surname><problem1></problem1><problem2></problem2><problem3></problem3><problem4></problem4><problem5></problem5><problem6></problem6><total>23</total><rank>113</rank><award></award></contestant><contestant id="10446">
<code>CAN</code><name>David</name><surname>Bernier</surname><problem1>0</problem1><problem2>2</problem2><problem3>7</problem3><problem4>7</problem4><problem5>0</problem5><problem6>7</problem6><total>23</total><rank>113</rank><award></award></contestant><contestant id="16722">
<code>VEN</code><name>Maria Cristina</name><surname>Pereyra</surname><problem1></problem1><problem2></problem2><problem3></problem3><problem4></problem4><problem5></problem5><problem6></problem6><total>23</total><rank>113</rank><award></award></contestant><contestant id="10476">
<code>YUG</code><name>Radovan</name><surname>Jevtić</surname><problem1></problem1><problem2></problem2><problem3></problem3><problem4></problem4><problem5></problem5><problem6></problem6><total>23</total><rank>113</rank><award></award></contestant><contestant id="10428">
<code>AUS</code><name>Alan</name><surname>Blair</surname><problem1></problem1><problem2></problem2><problem3></problem3><problem4></problem4><problem5></problem5><problem6></problem6><total>22</total><rank>117</rank><award></award></contestant><contestant id="16649">
<code>CUB</code><name>Domingo</name><surname>Louis</surname><problem1></problem1><problem2></problem2><problem3></problem3><problem4></problem4><problem5></problem5><problem6></problem6><total>22</total><rank>117</rank><award></award></contestant><contestant id="16700">
<code>SWE</code><name>Bo</name><surname>Bernhardsson</surname><problem1></problem1><problem2></problem2><problem3></problem3><problem4></problem4><problem5></problem5><problem6></problem6><total>22</total><rank>117</rank><award></award></contestant><contestant id="16621">
<code>AUT</code><name>Gerhard</name><surname>Wöginger</surname><problem1>1</problem1><problem2>4</problem2><problem3>7</problem3><problem4>4</problem4><problem5>1</problem5><problem6>4</problem6><total>21</total><rank>120</rank><award></award></contestant><contestant id="10441">
<code>BRA</code><name>Luis</name><surname>Cardoso</surname><problem1></problem1><problem2></problem2><problem3></problem3><problem4></problem4><problem5></problem5><problem6></problem6><total>21</total><rank>120</rank><award></award></contestant><contestant id="10442">
<code>BRA</code><name>Alexandre</name><surname>Chuva</surname><problem1></problem1><problem2></problem2><problem3></problem3><problem4></problem4><problem5></problem5><problem6></problem6><total>21</total><rank>120</rank><award></award></contestant><contestant id="10443">
<code>BRA</code><name>Tomas Pelosi</name><surname>Filho</surname><problem1></problem1><problem2></problem2><problem3></problem3><problem4></problem4><problem5></problem5><problem6></problem6><total>21</total><rank>120</rank><award></award></contestant><contestant id="16701">
<code>SWE</code><name>Ulf</name><surname>Carlsson</surname><problem1></problem1><problem2></problem2><problem3></problem3><problem4></problem4><problem5></problem5><problem6></problem6><total>20</total><rank>124</rank><award></award></contestant><contestant id="10479">
<code>YUG</code><name>Dragan</name><surname>Vukotić</surname><problem1></problem1><problem2></problem2><problem3></problem3><problem4></problem4><problem5></problem5><problem6></problem6><total>20</total><rank>124</rank><award></award></contestant><contestant id="16651">
<code>CUB</code><name>Jorge L.</name><surname>Barreras</surname><problem1></problem1><problem2></problem2><problem3></problem3><problem4></problem4><problem5></problem5><problem6></problem6><total>19</total><rank>126</rank><award></award></contestant><contestant id="16675">
<code>FRA</code><name>Marc</name><surname>Rosso</surname><problem1></problem1><problem2></problem2><problem3></problem3><problem4></problem4><problem5></problem5><problem6></problem6><total>18</total><rank>127</rank><award></award></contestant><contestant id="15990">
<code>POL</code><name>Jerzy</name><surname>Ciosłowski</surname><problem1></problem1><problem2></problem2><problem3></problem3><problem4></problem4><problem5></problem5><problem6></problem6><total>18</total><rank>127</rank><award></award></contestant><contestant id="16707">
<code>SWE</code><name>Bo</name><surname>Sundborg</surname><problem1></problem1><problem2></problem2><problem3></problem3><problem4></problem4><problem5></problem5><problem6></problem6><total>18</total><rank>127</rank><award></award></contestant><contestant id="16709">
<code>TUN</code><name>?</name><surname>?</surname><problem1></problem1><problem2></problem2><problem3></problem3><problem4></problem4><problem5></problem5><problem6></problem6><total>18</total><rank>127</rank><award></award></contestant><contestant id="10432">
<code>AUS</code><name>Stephen</name><surname>McKay</surname><problem1></problem1><problem2></problem2><problem3></problem3><problem4></problem4><problem5></problem5><problem6></problem6><total>17</total><rank>131</rank><award></award></contestant><contestant id="10440">
<code>BRA</code><name>Antonio José Madeira</name><surname>Domingues</surname><problem1></problem1><problem2></problem2><problem3></problem3><problem4></problem4><problem5></problem5><problem6></problem6><total>17</total><rank>131</rank><award></award></contestant><contestant id="16662">
<code>FIN</code><name>Ilkka</name><surname>Kiema</surname><problem1></problem1><problem2></problem2><problem3></problem3><problem4></problem4><problem5></problem5><problem6></problem6><total>17</total><rank>131</rank><award></award></contestant><contestant id="10462">
<code>NLD</code><name>Erick</name><surname>de Vries</surname><problem1>0</problem1><problem2>2</problem2><problem3>1</problem3><problem4>0</problem4><problem5>7</problem5><problem6>7</problem6><total>17</total><rank>131</rank><award></award></contestant><contestant id="16702">
<code>SWE</code><name>Arndt</name><surname>Jonasson</surname><problem1></problem1><problem2></problem2><problem3></problem3><problem4></problem4><problem5></problem5><problem6></problem6><total>17</total><rank>131</rank><award></award></contestant><contestant id="10447">
<code>CAN</code><name>John</name><surname>Bowman</surname><problem1>1</problem1><problem2>2</problem2><problem3>0</problem3><problem4>3</problem4><problem5>3</problem5><problem6>7</problem6><total>16</total><rank>136</rank><award></award></contestant><contestant id="16688">
<code>ISR</code><name>Leonard</name><surname>Shulman</surname><problem1></problem1><problem2></problem2><problem3></problem3><problem4></problem4><problem5></problem5><problem6></problem6><total>16</total><rank>136</rank><award></award></contestant><contestant id="10461">
<code>NLD</code><name>Sieds</name><surname>van de Schaaf</surname><problem1>1</problem1><problem2>2</problem2><problem3>3</problem3><problem4>4</problem4><problem5>6</problem5><problem6>0</problem6><total>16</total><rank>136</rank><award></award></contestant><contestant id="16669">
<code>FRA</code><name>Jean-François</name><surname>Bensahel</surname><problem1></problem1><problem2></problem2><problem3></problem3><problem4></problem4><problem5></problem5><problem6></problem6><total>15</total><rank>139</rank><award></award></contestant><contestant id="16680">
<code>HEL</code><name>?</name><surname>?</surname><problem1></problem1><problem2></problem2><problem3></problem3><problem4></problem4><problem5></problem5><problem6></problem6><total>15</total><rank>139</rank><award></award></contestant><contestant id="10439">
<code>BRA</code><name>Antonio Caldas</name><surname>Neto</surname><problem1></problem1><problem2></problem2><problem3></problem3><problem4></problem4><problem5></problem5><problem6></problem6><total>14</total><rank>141</rank><award></award></contestant><contestant id="16639">
<code>COL</code><name>Nelson</name><surname>Medina</surname><problem1></problem1><problem2></problem2><problem3></problem3><problem4></problem4><problem5></problem5><problem6></problem6><total>14</total><rank>141</rank><award></award></contestant><contestant id="16645">
<code>COL</code><name>Herbert</name><surname>Suárez</surname><problem1></problem1><problem2></problem2><problem3></problem3><problem4></problem4><problem5></problem5><problem6></problem6><total>14</total><rank>141</rank><award></award></contestant><contestant id="16646">
<code>COL</code><name>Ricardo</name><surname>Vélez</surname><problem1></problem1><problem2></problem2><problem3></problem3><problem4></problem4><problem5></problem5><problem6></problem6><total>14</total><rank>141</rank><award></award></contestant><contestant id="16653">
<code>CUB</code><name>Raul</name><surname>Perez</surname><problem1></problem1><problem2></problem2><problem3></problem3><problem4></problem4><problem5></problem5><problem6></problem6><total>14</total><rank>141</rank><award></award></contestant><contestant id="16683">
<code>HEL</code><name>?</name><surname>?</surname><problem1></problem1><problem2></problem2><problem3></problem3><problem4></problem4><problem5></problem5><problem6></problem6><total>14</total><rank>141</rank><award></award></contestant><contestant id="16708">
<code>TUN</code><name>?</name><surname>?</surname><problem1></problem1><problem2></problem2><problem3></problem3><problem4></problem4><problem5></problem5><problem6></problem6><total>14</total><rank>141</rank><award></award></contestant><contestant id="16720">
<code>VEN</code><name>Gustavo</name><surname>Lau</surname><problem1></problem1><problem2></problem2><problem3></problem3><problem4></problem4><problem5></problem5><problem6></problem6><total>14</total><rank>141</rank><award></award></contestant><contestant id="10429">
<code>AUS</code><name>Jim</name><surname>Farmer</surname><problem1></problem1><problem2></problem2><problem3></problem3><problem4></problem4><problem5></problem5><problem6></problem6><total>13</total><rank>149</rank><award></award></contestant><contestant id="16630">
<code>BRA</code><name>Henrique</name><surname>Mendes</surname><problem1></problem1><problem2></problem2><problem3></problem3><problem4></problem4><problem5></problem5><problem6></problem6><total>13</total><rank>149</rank><award></award></contestant><contestant id="16641">
<code>COL</code><name>Rodrigo</name><surname>Calderón</surname><problem1></problem1><problem2></problem2><problem3></problem3><problem4></problem4><problem5></problem5><problem6></problem6><total>13</total><rank>149</rank><award></award></contestant><contestant id="16644">
<code>COL</code><name>José</name><surname>Guterman</surname><problem1></problem1><problem2></problem2><problem3></problem3><problem4></problem4><problem5></problem5><problem6></problem6><total>13</total><rank>149</rank><award></award></contestant><contestant id="16640">
<code>COL</code><name>Mario</name><surname>Mejia</surname><problem1></problem1><problem2></problem2><problem3></problem3><problem4></problem4><problem5></problem5><problem6></problem6><total>13</total><rank>149</rank><award></award></contestant><contestant id="16678">
<code>HEL</code><name>?</name><surname>?</surname><problem1></problem1><problem2></problem2><problem3></problem3><problem4></problem4><problem5></problem5><problem6></problem6><total>13</total><rank>149</rank><award></award></contestant><contestant id="16679">
<code>HEL</code><name>?</name><surname>?</surname><problem1></problem1><problem2></problem2><problem3></problem3><problem4></problem4><problem5></problem5><problem6></problem6><total>13</total><rank>149</rank><award></award></contestant><contestant id="10430">
<code>AUS</code><name>Geoffrey</name><surname>Heenan</surname><problem1></problem1><problem2></problem2><problem3></problem3><problem4></problem4><problem5></problem5><problem6></problem6><total>12</total><rank>156</rank><award></award></contestant><contestant id="10433">
<code>AUS</code><name>Kenneth</name><surname>Ross</surname><problem1></problem1><problem2></problem2><problem3></problem3><problem4></problem4><problem5></problem5><problem6></problem6><total>12</total><rank>156</rank><award></award></contestant><contestant id="16650">
<code>CUB</code><name>René</name><surname>Dager Salomon</surname><problem1></problem1><problem2></problem2><problem3></problem3><problem4></problem4><problem5></problem5><problem6></problem6><total>12</total><rank>156</rank><award></award></contestant><contestant id="16682">
<code>HEL</code><name>?</name><surname>?</surname><problem1></problem1><problem2></problem2><problem3></problem3><problem4></problem4><problem5></problem5><problem6></problem6><total>12</total><rank>156</rank><award></award></contestant><contestant id="16642">
<code>COL</code><name>Marcos</name><surname>Lederman</surname><problem1></problem1><problem2></problem2><problem3></problem3><problem4></problem4><problem5></problem5><problem6></problem6><total>11</total><rank>160</rank><award></award></contestant><contestant id="16677">
<code>HEL</code><name>?</name><surname>?</surname><problem1></problem1><problem2></problem2><problem3></problem3><problem4></problem4><problem5></problem5><problem6></problem6><total>11</total><rank>160</rank><award></award></contestant><contestant id="10431">
<code>AUS</code><name>Wing</name><surname>On Lam</surname><problem1></problem1><problem2></problem2><problem3></problem3><problem4></problem4><problem5></problem5><problem6></problem6><total>10</total><rank>162</rank><award></award></contestant><contestant id="16663">
<code>FIN</code><name>Kari</name><surname>Kinaret</surname><problem1></problem1><problem2></problem2><problem3></problem3><problem4></problem4><problem5></problem5><problem6></problem6><total>10</total><rank>162</rank><award></award></contestant><contestant id="16652">
<code>CUB</code><name>Marco A.</name><surname>Gonzalez</surname><problem1></problem1><problem2></problem2><problem3></problem3><problem4></problem4><problem5></problem5><problem6></problem6><total>9</total><rank>164</rank><award></award></contestant><contestant id="16665">
<code>FIN</code><name>Timo</name><surname>Rönkkö</surname><problem1></problem1><problem2></problem2><problem3></problem3><problem4></problem4><problem5></problem5><problem6></problem6><total>9</total><rank>164</rank><award></award></contestant><contestant id="16718">
<code>VEN</code><name>Roberto</name><surname>Cavalieros</surname><problem1></problem1><problem2></problem2><problem3></problem3><problem4></problem4><problem5></problem5><problem6></problem6><total>9</total><rank>164</rank><award></award></contestant><contestant id="10434">
<code>AUS</code><name>Ken</name><surname>Skinner</surname><problem1>4</problem1><problem2>0</problem2><problem3>0</problem3><problem4>2</problem4><problem5>0</problem5><problem6>2</problem6><total>8</total><rank>167</rank><award></award></contestant><contestant id="16672">
<code>FRA</code><name>Didier</name><surname>Casserau</surname><problem1></problem1><problem2></problem2><problem3></problem3><problem4></problem4><problem5></problem5><problem6></problem6><total>8</total><rank>167</rank><award></award></contestant><contestant id="16626">
<code>BEL</code><name>Nanna</name><surname>Gillis</surname><problem1></problem1><problem2></problem2><problem3></problem3><problem4></problem4><problem5></problem5><problem6></problem6><total>6</total><rank>169</rank><award></award></contestant><contestant id="16654">
<code>CUB</code><name>Ernesto</name><surname>Moreno Frias</surname><problem1></problem1><problem2></problem2><problem3></problem3><problem4></problem4><problem5></problem5><problem6></problem6><total>6</total><rank>169</rank><award></award></contestant><contestant id="16716">
<code>VEN</code><name>Boris</name><surname>Ackerman</surname><problem1></problem1><problem2></problem2><problem3></problem3><problem4></problem4><problem5></problem5><problem6></problem6><total>6</total><rank>169</rank><award></award></contestant><contestant id="16692">
<code>MEX</code><name>Francisco Javier</name><surname>López López</surname><problem1></problem1><problem2></problem2><problem3></problem3><problem4></problem4><problem5></problem5><problem6></problem6><total>4</total><rank>172</rank><award></award></contestant><contestant id="16719">
<code>VEN</code><name>Oscar</name><surname>Dos Reis</surname><problem1></problem1><problem2></problem2><problem3></problem3><problem4></problem4><problem5></problem5><problem6></problem6><total>4</total><rank>172</rank><award></award></contestant><contestant id="16721">
<code>VEN</code><name>Moisés</name><surname>Lejter</surname><problem1></problem1><problem2></problem2><problem3></problem3><problem4></problem4><problem5></problem5><problem6></problem6><total>4</total><rank>172</rank><award></award></contestant><contestant id="16628">
<code>BEL</code><name>Lea</name><surname>Elst</surname><problem1></problem1><problem2></problem2><problem3></problem3><problem4></problem4><problem5></problem5><problem6></problem6><total>3</total><rank>175</rank><award></award></contestant><contestant id="16627">
<code>BEL</code><name>Marie-Anne</name><surname>Loones</surname><problem1></problem1><problem2></problem2><problem3></problem3><problem4></problem4><problem5></problem5><problem6></problem6><total>3</total><rank>175</rank><award></award></contestant><contestant id="16629">
<code>BEL</code><name>Guido</name><surname>Max</surname><problem1></problem1><problem2></problem2><problem3></problem3><problem4></problem4><problem5></problem5><problem6></problem6><total>3</total><rank>175</rank><award></award></contestant><contestant id="16691">
<code>MEX</code><name>Ciro Filemón</name><surname>Flores Riviera</surname><problem1></problem1><problem2></problem2><problem3></problem3><problem4></problem4><problem5></problem5><problem6></problem6><total>3</total><rank>175</rank><award></award></contestant><contestant id="16717">
<code>VEN</code><name>Nisin</name><surname>Aquinin</surname><problem1></problem1><problem2></problem2><problem3></problem3><problem4></problem4><problem5></problem5><problem6></problem6><total>3</total><rank>175</rank><award></award></contestant><contestant id="16681">
<code>HEL</code><name>?</name><surname>?</surname><problem1></problem1><problem2></problem2><problem3></problem3><problem4></problem4><problem5></problem5><problem6></problem6><total>2</total><rank>180</rank><award></award></contestant><contestant id="16694">
<code>MEX</code><name>Sergio</name><surname>Barajas Félix</surname><problem1></problem1><problem2></problem2><problem3></problem3><problem4></problem4><problem5></problem5><problem6></problem6><total>2</total><rank>180</rank><award></award></contestant><contestant id="16693">
<code>MEX</code><name>Aldo René</name><surname>Maldonaldo Duarte</surname><problem1></problem1><problem2></problem2><problem3></problem3><problem4></problem4><problem5></problem5><problem6></problem6><total>2</total><rank>180</rank><award></award></contestant><contestant id="16643">
<code>COL</code><name>Tatiana</name><surname>Toro</surname><problem1></problem1><problem2></problem2><problem3></problem3><problem4></problem4><problem5></problem5><problem6></problem6><total>1</total><rank>183</rank><award></award></contestant><contestant id="16695">
<code>MEX</code><name>Raúl</name><surname>Medina Hernández</surname><problem1></problem1><problem2></problem2><problem3></problem3><problem4></problem4><problem5></problem5><problem6></problem6><total>1</total><rank>183</rank><award></award></contestant><contestant id="16723">
<code>VEN</code><name>Marlon</name><surname>Sánchez</surname><problem1></problem1><problem2></problem2><problem3></problem3><problem4></problem4><problem5></problem5><problem6></problem6><total>1</total><rank>183</rank><award></award></contestant></yearIR>